pdf_to_wordcloud/__init__.py
pdf_to_wordcloud/pdf_to_wordcloud.py
pdf_to_wordcloud/data/mask.png
pdf_to_wordcloud/data/stopwords.txt
pdf_to_wordcloud-0.0.8.dist-info/LICENSE
pdf_to_wordcloud-0.0.8.dist-info/METADATA
pdf_to_wordcloud-0.0.8.dist-info/WHEEL
pdf_to_wordcloud-0.0.8.dist-info/entry_points.txt
pdf_to_wordcloud-0.0.8.dist-info/top_level.txt
pdf_to_wordcloud-0.0.8.dist-info/RECORD
