Metadata-Version: 2.1
Name: pdf-to-wordcloud
Version: 0.0.8
Summary: Generates a word cloud from a given PDF
Home-page: https://github.com/rybinmj/pdf_to_wordcloud
Author: Matt Rybin
Author-email: rybinmj@gmail.com
Classifier: Programming Language :: Python :: 3
Classifier: License :: OSI Approved :: MIT License
Classifier: Operating System :: OS Independent
Requires-Python: >=3.6
License-File: LICENSE
Requires-Dist: pdfplumber
Requires-Dist: nltk
Requires-Dist: pandas
Requires-Dist: numpy
Requires-Dist: matplotlib
Requires-Dist: wordcloud
